{
    "0": [
        0,
        509,
        651
    ],
    "1": [
        1,
        206
    ],
    "2": [
        2
    ],
    "3": [
        3,
        17,
        512
    ],
    "4": [
        4,
        171,
        602
    ],
    "5": [
        5,
        202,
        419
    ],
    "6": [
        6,
        74,
        335
    ],
    "7": [
        7,
        150,
        158
    ],
    "8": [
        8,
        1465
    ],
    "9": [
        9,
        116,
        132
    ],
    "10": [
        10,
        65,
        76
    ],
    "11": [
        11,
        277,
        492
    ],
    "12": [
        12
    ],
    "13": [
        13,
        451,
        918
    ],
    "14": [
        14,
        104,
        292
    ],
    "15": [
        15,
        605
    ],
    "16": [
        16,
        947,
        1058
    ],
    "17": [
        18,
        304,
        391
    ],
    "18": [
        19
    ],
    "19": [
        20,
        487,
        702
    ],
    "20": [
        21,
        123,
        187
    ],
    "21": [
        22,
        258,
        413
    ],
    "22": [
        23,
        145,
        295
    ],
    "23": [
        24,
        1817
    ],
    "24": [
        25,
        92,
        98
    ],
    "25": [
        26,
        1449
    ],
    "26": [
        27,
        781,
        1519
    ],
    "27": [
        28,
        446,
        850
    ],
    "28": [
        29,
        80,
        105
    ],
    "29": [
        30,
        193,
        1196
    ],
    "30": [
        31,
        1181,
        1509
    ],
    "31": [
        32
    ],
    "32": [
        33,
        186
    ],
    "33": [
        34
    ],
    "34": [
        35
    ],
    "35": [
        36,
        60,
        183
    ],
    "36": [
        37
    ],
    "37": [
        38,
        41,
        165
    ],
    "38": [
        39
    ],
    "39": [
        40,
        694,
        816
    ],
    "40": [
        42
    ],
    "41": [
        43,
        414
    ],
    "42": [
        44
    ],
    "43": [
        45,
        410,
        434
    ],
    "44": [
        46,
        985,
        1128
    ],
    "45": [
        47,
        305,
        377
    ],
    "46": [
        48,
        1090,
        1735
    ],
    "47": [
        49,
        78,
        408
    ],
    "48": [
        50,
        468,
        659
    ],
    "49": [
        51
    ],
    "50": [
        52,
        293
    ],
    "51": [
        53,
        448,
        554
    ],
    "52": [
        54,
        706
    ],
    "53": [
        55,
        61,
        79
    ],
    "54": [
        56
    ],
    "55": [
        57,
        919
    ],
    "56": [
        58,
        99,
        164
    ],
    "57": [
        59,
        1433
    ],
    "58": [
        62,
        1357,
        1872
    ],
    "59": [
        63,
        94,
        642
    ],
    "60": [
        64
    ],
    "61": [
        66,
        508,
        646
    ],
    "62": [
        67,
        795,
        910
    ],
    "63": [
        68
    ],
    "64": [
        69,
        1481,
        1560
    ],
    "65": [
        70
    ],
    "66": [
        71
    ],
    "67": [
        72
    ],
    "68": [
        73,
        84,
        97
    ],
    "69": [
        75,
        765,
        766
    ],
    "70": [
        77,
        1078
    ],
    "71": [
        81
    ],
    "72": [
        82
    ],
    "73": [
        83,
        1281
    ],
    "74": [
        85,
        599
    ],
    "75": [
        86,
        1002,
        1003
    ],
    "76": [
        87,
        90,
        720
    ],
    "77": [
        88
    ],
    "78": [
        89,
        96,
        121
    ],
    "79": [
        91,
        221,
        465
    ],
    "80": [
        93,
        1087,
        1743
    ],
    "81": [
        95
    ],
    "82": [
        100
    ],
    "83": [
        101
    ],
    "84": [
        102
    ],
    "85": [
        103
    ],
    "86": [
        106,
        339,
        385
    ],
    "87": [
        107
    ],
    "88": [
        108
    ],
    "89": [
        109
    ],
    "90": [
        110,
        255,
        673
    ],
    "91": [
        111,
        531,
        545
    ],
    "92": [
        112,
        522,
        935
    ],
    "93": [
        113,
        582,
        607
    ],
    "94": [
        114,
        353,
        473
    ],
    "95": [
        115
    ],
    "96": [
        117
    ],
    "97": [
        118,
        317,
        319
    ],
    "98": [
        119,
        926,
        1138
    ],
    "99": [
        120,
        230,
        510
    ],
    "100": [
        122,
        684,
        830
    ],
    "101": [
        124
    ],
    "102": [
        125
    ],
    "103": [
        126,
        1192,
        1798
    ],
    "104": [
        127
    ],
    "105": [
        128
    ],
    "106": [
        129,
        166,
        215
    ],
    "107": [
        130
    ],
    "108": [
        131,
        254,
        627
    ],
    "109": [
        133,
        344,
        553
    ],
    "110": [
        134
    ],
    "111": [
        135,
        322,
        482
    ],
    "112": [
        136
    ],
    "113": [
        137
    ],
    "114": [
        138
    ],
    "115": [
        139,
        227
    ],
    "116": [
        140,
        811,
        864
    ],
    "117": [
        141,
        415,
        709
    ],
    "118": [
        142
    ],
    "119": [
        143,
        224,
        860
    ],
    "120": [
        144,
        1621
    ],
    "121": [
        146
    ],
    "122": [
        147,
        155,
        983
    ],
    "123": [
        148,
        1925
    ],
    "124": [
        149,
        496,
        548
    ],
    "125": [
        151
    ],
    "126": [
        152
    ],
    "127": [
        153
    ],
    "128": [
        154,
        229,
        237
    ],
    "129": [
        156
    ],
    "130": [
        157,
        1353,
        1512
    ],
    "131": [
        159,
        382,
        530
    ],
    "132": [
        160
    ],
    "133": [
        161
    ],
    "134": [
        162,
        461,
        739
    ],
    "135": [
        163,
        1212,
        1388
    ],
    "136": [
        167
    ],
    "137": [
        168,
        1910
    ],
    "138": [
        169,
        403,
        469
    ],
    "139": [
        170,
        219,
        1125
    ],
    "140": [
        172,
        197,
        240
    ],
    "141": [
        173,
        281,
        284
    ],
    "142": [
        174
    ],
    "143": [
        175
    ],
    "144": [
        176,
        350
    ],
    "145": [
        177,
        310,
        528
    ],
    "146": [
        178,
        314,
        474
    ],
    "147": [
        179,
        1024,
        1331
    ],
    "148": [
        180
    ],
    "149": [
        181,
        271,
        274
    ],
    "150": [
        182,
        759,
        1886
    ],
    "151": [
        184,
        316,
        481
    ],
    "152": [
        185
    ],
    "153": [
        188
    ],
    "154": [
        189,
        442,
        1060
    ],
    "155": [
        190,
        1161,
        1699
    ],
    "156": [
        191,
        518
    ],
    "157": [
        192
    ],
    "158": [
        194,
        1824
    ],
    "159": [
        195
    ],
    "160": [
        196
    ],
    "161": [
        198
    ],
    "162": [
        199,
        205,
        1036
    ],
    "163": [
        200
    ],
    "164": [
        201,
        1160,
        1217
    ],
    "165": [
        203,
        247
    ],
    "166": [
        204
    ],
    "167": [
        207
    ],
    "168": [
        208
    ],
    "169": [
        209,
        1441
    ],
    "170": [
        210,
        783,
        870
    ],
    "171": [
        211,
        543
    ],
    "172": [
        212,
        222,
        573
    ],
    "173": [
        213
    ],
    "174": [
        214,
        1333
    ],
    "175": [
        216
    ],
    "176": [
        217,
        243,
        349
    ],
    "177": [
        218,
        1248,
        1644
    ],
    "178": [
        220
    ],
    "179": [
        223
    ],
    "180": [
        225,
        236,
        262
    ],
    "181": [
        226,
        536,
        863
    ],
    "182": [
        228,
        477,
        936
    ],
    "183": [
        231
    ],
    "184": [
        232
    ],
    "185": [
        233
    ],
    "186": [
        234,
        804,
        930
    ],
    "187": [
        235,
        875
    ],
    "188": [
        238,
        1332
    ],
    "189": [
        239
    ],
    "190": [
        241
    ],
    "191": [
        242,
        984,
        1528
    ],
    "192": [
        244,
        1052,
        1167
    ],
    "193": [
        245
    ],
    "194": [
        246
    ],
    "195": [
        248,
        578,
        719
    ],
    "196": [
        249,
        565,
        824
    ],
    "197": [
        250
    ],
    "198": [
        251
    ],
    "199": [
        252,
        557,
        774
    ],
    "200": [
        253,
        1233,
        1362
    ],
    "201": [
        256,
        968,
        1672
    ],
    "202": [
        257
    ],
    "203": [
        259,
        566,
        1423
    ],
    "204": [
        260,
        1919
    ],
    "205": [
        261,
        693,
        729
    ],
    "206": [
        263
    ],
    "207": [
        264
    ],
    "208": [
        265,
        268,
        524
    ],
    "209": [
        266
    ],
    "210": [
        267,
        1544
    ],
    "211": [
        269
    ],
    "212": [
        270
    ],
    "213": [
        272,
        1505,
        1553
    ],
    "214": [
        273,
        439,
        561
    ],
    "215": [
        275
    ],
    "216": [
        276,
        338,
        404
    ],
    "217": [
        278
    ],
    "218": [
        279,
        342,
        1551
    ],
    "219": [
        280,
        288,
        1190
    ],
    "220": [
        282,
        761
    ],
    "221": [
        283
    ],
    "222": [
        285
    ],
    "223": [
        286,
        609,
        663
    ],
    "224": [
        287,
        417,
        494
    ],
    "225": [
        289,
        332,
        367
    ],
    "226": [
        290
    ],
    "227": [
        291,
        1051,
        1202
    ],
    "228": [
        294
    ],
    "229": [
        296,
        678,
        967
    ],
    "230": [
        297
    ],
    "231": [
        298,
        1611
    ],
    "232": [
        299,
        400,
        431
    ],
    "233": [
        300
    ],
    "234": [
        301
    ],
    "235": [
        302,
        1007,
        1782
    ],
    "236": [
        303,
        690,
        1310
    ],
    "237": [
        306
    ],
    "238": [
        307
    ],
    "239": [
        308,
        416,
        664
    ],
    "240": [
        309,
        579,
        587
    ],
    "241": [
        311,
        777,
        835
    ],
    "242": [
        312,
        1417
    ],
    "243": [
        313
    ],
    "244": [
        315,
        502
    ],
    "245": [
        318,
        422
    ],
    "246": [
        320,
        538,
        1547
    ],
    "247": [
        321
    ],
    "248": [
        323,
        1124
    ],
    "249": [
        324
    ],
    "250": [
        325
    ],
    "251": [
        326,
        796
    ],
    "252": [
        327
    ],
    "253": [
        328,
        1222,
        1286
    ],
    "254": [
        329,
        1564
    ],
    "255": [
        330,
        483,
        831
    ],
    "256": [
        331,
        1199,
        1540
    ],
    "257": [
        333,
        389,
        521
    ],
    "258": [
        334
    ],
    "259": [
        336,
        354,
        363
    ],
    "260": [
        337,
        376
    ],
    "261": [
        340,
        1630,
        1729
    ],
    "262": [
        341,
        1437
    ],
    "263": [
        343,
        583,
        726
    ],
    "264": [
        345,
        418,
        493
    ],
    "265": [
        346
    ],
    "266": [
        347,
        370,
        484
    ],
    "267": [
        348,
        815,
        1640
    ],
    "268": [
        351,
        356,
        780
    ],
    "269": [
        352,
        825,
        1080
    ],
    "270": [
        355
    ],
    "271": [
        357,
        562
    ],
    "272": [
        358,
        626
    ],
    "273": [
        359
    ],
    "274": [
        360,
        1745
    ],
    "275": [
        361,
        443,
        836
    ],
    "276": [
        362,
        595
    ],
    "277": [
        364
    ],
    "278": [
        365,
        1424
    ],
    "279": [
        366
    ],
    "280": [
        368
    ],
    "281": [
        369
    ],
    "282": [
        371,
        1862
    ],
    "283": [
        372,
        1277
    ],
    "284": [
        373
    ],
    "285": [
        374,
        444,
        769
    ],
    "286": [
        375,
        412,
        803
    ],
    "287": [
        378,
        1386,
        1755
    ],
    "288": [
        379,
        737,
        812
    ],
    "289": [
        380
    ],
    "290": [
        381,
        1585
    ],
    "291": [
        383
    ],
    "292": [
        384,
        523,
        756
    ],
    "293": [
        386
    ],
    "294": [
        387
    ],
    "295": [
        388
    ],
    "296": [
        390,
        1136,
        1756
    ],
    "297": [
        392
    ],
    "298": [
        393,
        466,
        535
    ],
    "299": [
        394
    ],
    "300": [
        395
    ],
    "301": [
        396
    ],
    "302": [
        397
    ],
    "303": [
        398
    ],
    "304": [
        399,
        1538
    ],
    "305": [
        401
    ],
    "306": [
        402,
        1243
    ],
    "307": [
        405
    ],
    "308": [
        406,
        1479
    ],
    "309": [
        407,
        1867
    ],
    "310": [
        409
    ],
    "311": [
        411,
        775,
        792
    ],
    "312": [
        420
    ],
    "313": [
        421
    ],
    "314": [
        423,
        748,
        876
    ],
    "315": [
        424
    ],
    "316": [
        425,
        652,
        833
    ],
    "317": [
        426
    ],
    "318": [
        427,
        462,
        517
    ],
    "319": [
        428
    ],
    "320": [
        429
    ],
    "321": [
        430
    ],
    "322": [
        432,
        581
    ],
    "323": [
        433
    ],
    "324": [
        435
    ],
    "325": [
        436
    ],
    "326": [
        437
    ],
    "327": [
        438,
        568,
        608
    ],
    "328": [
        440
    ],
    "329": [
        441,
        1213
    ],
    "330": [
        445
    ],
    "331": [
        447
    ],
    "332": [
        449,
        526,
        527
    ],
    "333": [
        450
    ],
    "334": [
        452,
        1860
    ],
    "335": [
        453,
        1629
    ],
    "336": [
        454
    ],
    "337": [
        455,
        1086,
        1488
    ],
    "338": [
        456,
        665,
        1358
    ],
    "339": [
        457,
        710,
        764
    ],
    "340": [
        458,
        925,
        1201
    ],
    "341": [
        459
    ],
    "342": [
        460,
        1366,
        1665
    ],
    "343": [
        463
    ],
    "344": [
        464
    ],
    "345": [
        467
    ],
    "346": [
        470
    ],
    "347": [
        471,
        632,
        1129
    ],
    "348": [
        472
    ],
    "349": [
        475,
        978,
        1522
    ],
    "350": [
        476,
        1157,
        1214
    ],
    "351": [
        478,
        1457,
        1463
    ],
    "352": [
        479
    ],
    "353": [
        480,
        961,
        963
    ],
    "354": [
        485
    ],
    "355": [
        486,
        1116,
        1169
    ],
    "356": [
        488,
        564,
        671
    ],
    "357": [
        489
    ],
    "358": [
        490
    ],
    "359": [
        491
    ],
    "360": [
        495
    ],
    "361": [
        497,
        1521
    ],
    "362": [
        498
    ],
    "363": [
        499
    ],
    "364": [
        500
    ],
    "365": [
        501,
        563,
        762
    ],
    "366": [
        503,
        878
    ],
    "367": [
        504,
        813,
        862
    ],
    "368": [
        505,
        837,
        879
    ],
    "369": [
        506
    ],
    "370": [
        507
    ],
    "371": [
        511
    ],
    "372": [
        513
    ],
    "373": [
        514,
        772,
        1026
    ],
    "374": [
        515,
        547,
        615
    ],
    "375": [
        516,
        588,
        639
    ],
    "376": [
        519
    ],
    "377": [
        520,
        715,
        906
    ],
    "378": [
        525
    ],
    "379": [
        529,
        1180,
        1523
    ],
    "380": [
        532
    ],
    "381": [
        533,
        1185
    ],
    "382": [
        534
    ],
    "383": [
        537,
        600,
        826
    ],
    "384": [
        539,
        1857
    ],
    "385": [
        540
    ],
    "386": [
        541,
        1518
    ],
    "387": [
        542,
        623,
        1369
    ],
    "388": [
        544
    ],
    "389": [
        546,
        1511,
        1584
    ],
    "390": [
        549
    ],
    "391": [
        550
    ],
    "392": [
        551
    ],
    "393": [
        552
    ],
    "394": [
        555,
        570,
        1035
    ],
    "395": [
        556
    ],
    "396": [
        558
    ],
    "397": [
        559
    ],
    "398": [
        560,
        981
    ],
    "399": [
        567,
        1356
    ],
    "400": [
        569,
        894,
        1316
    ],
    "401": [
        571
    ],
    "402": [
        572
    ],
    "403": [
        574,
        791,
        908
    ],
    "404": [
        575
    ],
    "405": [
        576
    ],
    "406": [
        577,
        1418,
        1464
    ],
    "407": [
        580
    ],
    "408": [
        584
    ],
    "409": [
        585,
        1226
    ],
    "410": [
        586
    ],
    "411": [
        589,
        691,
        695
    ],
    "412": [
        590,
        631,
        699
    ],
    "413": [
        591,
        1059
    ],
    "414": [
        592,
        898
    ],
    "415": [
        593,
        633
    ],
    "416": [
        594
    ],
    "417": [
        596,
        1829
    ],
    "418": [
        597,
        1367,
        1813
    ],
    "419": [
        598
    ],
    "420": [
        601,
        1695
    ],
    "421": [
        603
    ],
    "422": [
        604,
        844
    ],
    "423": [
        606,
        1149,
        1715
    ],
    "424": [
        610,
        1884
    ],
    "425": [
        611,
        1263,
        1759
    ],
    "426": [
        612
    ],
    "427": [
        613,
        1894
    ],
    "428": [
        614,
        855,
        1914
    ],
    "429": [
        616
    ],
    "430": [
        617,
        755,
        954
    ],
    "431": [
        618
    ],
    "432": [
        619
    ],
    "433": [
        620
    ],
    "434": [
        621
    ],
    "435": [
        622
    ],
    "436": [
        624,
        636,
        952
    ],
    "437": [
        625
    ],
    "438": [
        628
    ],
    "439": [
        629,
        1869
    ],
    "440": [
        630
    ],
    "441": [
        634
    ],
    "442": [
        635
    ],
    "443": [
        637
    ],
    "444": [
        638
    ],
    "445": [
        640
    ],
    "446": [
        641,
        800
    ],
    "447": [
        643
    ],
    "448": [
        644
    ],
    "449": [
        645
    ],
    "450": [
        647
    ],
    "451": [
        648,
        680,
        758
    ],
    "452": [
        649,
        1754
    ],
    "453": [
        650
    ],
    "454": [
        653,
        1797
    ],
    "455": [
        654
    ],
    "456": [
        655,
        1484
    ],
    "457": [
        656,
        1293,
        1435
    ],
    "458": [
        657
    ],
    "459": [
        658
    ],
    "460": [
        660,
        1407,
        1814
    ],
    "461": [
        661,
        1110,
        1236
    ],
    "462": [
        662
    ],
    "463": [
        666,
        1219
    ],
    "464": [
        667,
        1828,
        1908
    ],
    "465": [
        668,
        846,
        1023
    ],
    "466": [
        669
    ],
    "467": [
        670
    ],
    "468": [
        672
    ],
    "469": [
        674,
        911,
        1268
    ],
    "470": [
        675
    ],
    "471": [
        676,
        1904
    ],
    "472": [
        677
    ],
    "473": [
        679
    ],
    "474": [
        681,
        1360,
        1583
    ],
    "475": [
        682,
        1055,
        1419
    ],
    "476": [
        683,
        1779
    ],
    "477": [
        685
    ],
    "478": [
        686
    ],
    "479": [
        687,
        1144,
        1501
    ],
    "480": [
        688,
        869
    ],
    "481": [
        689,
        1085
    ],
    "482": [
        692
    ],
    "483": [
        696
    ],
    "484": [
        697
    ],
    "485": [
        698
    ],
    "486": [
        700,
        868,
        1653
    ],
    "487": [
        701
    ],
    "488": [
        703
    ],
    "489": [
        704
    ],
    "490": [
        705,
        1156,
        1500
    ],
    "491": [
        707
    ],
    "492": [
        708,
        767,
        788
    ],
    "493": [
        711
    ],
    "494": [
        712,
        1297,
        1520
    ],
    "495": [
        713,
        753,
        1098
    ],
    "496": [
        714,
        1057
    ],
    "497": [
        716,
        717,
        724
    ],
    "498": [
        718
    ],
    "499": [
        721
    ],
    "500": [
        722
    ],
    "501": [
        723,
        932,
        1393
    ],
    "502": [
        725
    ],
    "503": [
        727
    ],
    "504": [
        728,
        749,
        994
    ],
    "505": [
        730,
        808,
        874
    ],
    "506": [
        731
    ],
    "507": [
        732,
        742,
        1299
    ],
    "508": [
        733,
        1707
    ],
    "509": [
        734,
        909,
        1005
    ],
    "510": [
        735,
        1587,
        1740
    ],
    "511": [
        736
    ],
    "512": [
        738
    ],
    "513": [
        740,
        1873
    ],
    "514": [
        741
    ],
    "515": [
        743
    ],
    "516": [
        744,
        1275,
        1325
    ],
    "517": [
        745,
        992,
        1447
    ],
    "518": [
        746
    ],
    "519": [
        747,
        1112,
        1147
    ],
    "520": [
        750
    ],
    "521": [
        751,
        1498,
        1898
    ],
    "522": [
        752
    ],
    "523": [
        754
    ],
    "524": [
        757
    ],
    "525": [
        760
    ],
    "526": [
        763,
        1933
    ],
    "527": [
        768
    ],
    "528": [
        770,
        1224
    ],
    "529": [
        771
    ],
    "530": [
        773
    ],
    "531": [
        776,
        1628
    ],
    "532": [
        778
    ],
    "533": [
        779
    ],
    "534": [
        782
    ],
    "535": [
        784
    ],
    "536": [
        785
    ],
    "537": [
        786,
        1253,
        1346
    ],
    "538": [
        787
    ],
    "539": [
        789
    ],
    "540": [
        790
    ],
    "541": [
        793
    ],
    "542": [
        794,
        1209
    ],
    "543": [
        797
    ],
    "544": [
        798
    ],
    "545": [
        799
    ],
    "546": [
        801
    ],
    "547": [
        802
    ],
    "548": [
        805
    ],
    "549": [
        806
    ],
    "550": [
        807
    ],
    "551": [
        809
    ],
    "552": [
        810
    ],
    "553": [
        814,
        1006,
        1011
    ],
    "554": [
        817,
        1557,
        1582
    ],
    "555": [
        818
    ],
    "556": [
        819,
        1685
    ],
    "557": [
        820
    ],
    "558": [
        821
    ],
    "559": [
        822
    ],
    "560": [
        823,
        892,
        1404
    ],
    "561": [
        827,
        1751
    ],
    "562": [
        828,
        866,
        948
    ],
    "563": [
        829,
        1795
    ],
    "564": [
        832
    ],
    "565": [
        834,
        1256,
        1603
    ],
    "566": [
        838
    ],
    "567": [
        839
    ],
    "568": [
        840
    ],
    "569": [
        841
    ],
    "570": [
        842,
        880,
        1015
    ],
    "571": [
        843,
        1265
    ],
    "572": [
        845
    ],
    "573": [
        847
    ],
    "574": [
        848,
        1875
    ],
    "575": [
        849,
        928,
        1205
    ],
    "576": [
        851
    ],
    "577": [
        852
    ],
    "578": [
        853,
        1033,
        1287
    ],
    "579": [
        854
    ],
    "580": [
        856
    ],
    "581": [
        857,
        1121
    ],
    "582": [
        858,
        1207,
        1311
    ],
    "583": [
        859
    ],
    "584": [
        861
    ],
    "585": [
        865,
        946
    ],
    "586": [
        867,
        1241,
        1613
    ],
    "587": [
        871,
        922,
        964
    ],
    "588": [
        872
    ],
    "589": [
        873,
        1030,
        1122
    ],
    "590": [
        877,
        965,
        1014
    ],
    "591": [
        881
    ],
    "592": [
        882
    ],
    "593": [
        883,
        1436
    ],
    "594": [
        884,
        1073
    ],
    "595": [
        885
    ],
    "596": [
        886
    ],
    "597": [
        887
    ],
    "598": [
        888
    ],
    "599": [
        889,
        1634
    ],
    "600": [
        890,
        1513,
        1605
    ],
    "601": [
        891
    ],
    "602": [
        893,
        929,
        988
    ],
    "603": [
        895
    ],
    "604": [
        896,
        1056,
        1184
    ],
    "605": [
        897,
        1221,
        1372
    ],
    "606": [
        899
    ],
    "607": [
        900
    ],
    "608": [
        901,
        1375
    ],
    "609": [
        902
    ],
    "610": [
        903
    ],
    "611": [
        904
    ],
    "612": [
        905
    ],
    "613": [
        907,
        1173,
        1183
    ],
    "614": [
        912
    ],
    "615": [
        913
    ],
    "616": [
        914
    ],
    "617": [
        915
    ],
    "618": [
        916,
        1669
    ],
    "619": [
        917
    ],
    "620": [
        920
    ],
    "621": [
        921
    ],
    "622": [
        923,
        1009,
        1302
    ],
    "623": [
        924
    ],
    "624": [
        927
    ],
    "625": [
        931
    ],
    "626": [
        933
    ],
    "627": [
        934
    ],
    "628": [
        937
    ],
    "629": [
        938,
        1182,
        1251
    ],
    "630": [
        939,
        1642,
        1877
    ],
    "631": [
        940,
        1029,
        1206
    ],
    "632": [
        941,
        956,
        957
    ],
    "633": [
        942
    ],
    "634": [
        943,
        1234,
        1317
    ],
    "635": [
        944,
        1131
    ],
    "636": [
        945,
        1010,
        1561
    ],
    "637": [
        949,
        1309,
        1396
    ],
    "638": [
        950
    ],
    "639": [
        951
    ],
    "640": [
        953
    ],
    "641": [
        955
    ],
    "642": [
        958
    ],
    "643": [
        959,
        1624,
        1792
    ],
    "644": [
        960
    ],
    "645": [
        962
    ],
    "646": [
        966
    ],
    "647": [
        969,
        1510,
        1885
    ],
    "648": [
        970
    ],
    "649": [
        971,
        1111,
        1802
    ],
    "650": [
        972
    ],
    "651": [
        973,
        997,
        1276
    ],
    "652": [
        974
    ],
    "653": [
        975
    ],
    "654": [
        976
    ],
    "655": [
        977
    ],
    "656": [
        979,
        1075,
        1351
    ],
    "657": [
        980,
        1703
    ],
    "658": [
        982,
        1170,
        1412
    ],
    "659": [
        986,
        1279,
        1280
    ],
    "660": [
        987
    ],
    "661": [
        989
    ],
    "662": [
        990
    ],
    "663": [
        991
    ],
    "664": [
        993
    ],
    "665": [
        995
    ],
    "666": [
        996
    ],
    "667": [
        998
    ],
    "668": [
        999
    ],
    "669": [
        1000
    ],
    "670": [
        1001
    ],
    "671": [
        1004,
        1812
    ],
    "672": [
        1008,
        1313,
        1722
    ],
    "673": [
        1012
    ],
    "674": [
        1013
    ],
    "675": [
        1016,
        1177,
        1194
    ],
    "676": [
        1017,
        1113,
        1146
    ],
    "677": [
        1018
    ],
    "678": [
        1019,
        1846
    ],
    "679": [
        1020
    ],
    "680": [
        1021,
        1204,
        1575
    ],
    "681": [
        1022,
        1171,
        1188
    ],
    "682": [
        1025,
        1104,
        1228
    ],
    "683": [
        1027
    ],
    "684": [
        1028
    ],
    "685": [
        1031
    ],
    "686": [
        1032
    ],
    "687": [
        1034,
        1065,
        1164
    ],
    "688": [
        1037
    ],
    "689": [
        1038
    ],
    "690": [
        1039,
        1220,
        1285
    ],
    "691": [
        1040
    ],
    "692": [
        1041,
        1215,
        1434
    ],
    "693": [
        1042
    ],
    "694": [
        1043
    ],
    "695": [
        1044
    ],
    "696": [
        1045
    ],
    "697": [
        1046,
        1306,
        1361
    ],
    "698": [
        1047,
        1444,
        1903
    ],
    "699": [
        1048
    ],
    "700": [
        1049
    ],
    "701": [
        1050
    ],
    "702": [
        1053,
        1825,
        1913
    ],
    "703": [
        1054
    ],
    "704": [
        1061,
        1127,
        1261
    ],
    "705": [
        1062
    ],
    "706": [
        1063
    ],
    "707": [
        1064
    ],
    "708": [
        1066
    ],
    "709": [
        1067
    ],
    "710": [
        1068
    ],
    "711": [
        1069,
        1721,
        1844
    ],
    "712": [
        1070
    ],
    "713": [
        1071,
        1668
    ],
    "714": [
        1072
    ],
    "715": [
        1074
    ],
    "716": [
        1076
    ],
    "717": [
        1077
    ],
    "718": [
        1079
    ],
    "719": [
        1081,
        1225
    ],
    "720": [
        1082
    ],
    "721": [
        1083,
        1117,
        1352
    ],
    "722": [
        1084
    ],
    "723": [
        1088
    ],
    "724": [
        1089
    ],
    "725": [
        1091,
        1141,
        1227
    ],
    "726": [
        1092
    ],
    "727": [
        1093
    ],
    "728": [
        1094
    ],
    "729": [
        1095
    ],
    "730": [
        1096,
        1166,
        1257
    ],
    "731": [
        1097
    ],
    "732": [
        1099
    ],
    "733": [
        1100,
        1178
    ],
    "734": [
        1101
    ],
    "735": [
        1102
    ],
    "736": [
        1103
    ],
    "737": [
        1105,
        1238,
        1442
    ],
    "738": [
        1106
    ],
    "739": [
        1107,
        1535
    ],
    "740": [
        1108
    ],
    "741": [
        1109,
        1142,
        1242
    ],
    "742": [
        1114
    ],
    "743": [
        1115
    ],
    "744": [
        1118,
        1614,
        1681
    ],
    "745": [
        1119
    ],
    "746": [
        1120
    ],
    "747": [
        1123
    ],
    "748": [
        1126
    ],
    "749": [
        1130
    ],
    "750": [
        1132
    ],
    "751": [
        1133
    ],
    "752": [
        1134
    ],
    "753": [
        1135,
        1878
    ],
    "754": [
        1137
    ],
    "755": [
        1139
    ],
    "756": [
        1140
    ],
    "757": [
        1143
    ],
    "758": [
        1145,
        1649
    ],
    "759": [
        1148,
        1470,
        1507
    ],
    "760": [
        1150,
        1648,
        1928
    ],
    "761": [
        1151
    ],
    "762": [
        1152
    ],
    "763": [
        1153
    ],
    "764": [
        1154
    ],
    "765": [
        1155
    ],
    "766": [
        1158
    ],
    "767": [
        1159,
        1406,
        1558
    ],
    "768": [
        1162
    ],
    "769": [
        1163
    ],
    "770": [
        1165
    ],
    "771": [
        1168
    ],
    "772": [
        1172
    ],
    "773": [
        1174,
        1334
    ],
    "774": [
        1175
    ],
    "775": [
        1176
    ],
    "776": [
        1179
    ],
    "777": [
        1186
    ],
    "778": [
        1187
    ],
    "779": [
        1189
    ],
    "780": [
        1191
    ],
    "781": [
        1193
    ],
    "782": [
        1195
    ],
    "783": [
        1197
    ],
    "784": [
        1198
    ],
    "785": [
        1200
    ],
    "786": [
        1203
    ],
    "787": [
        1208,
        1210,
        1467
    ],
    "788": [
        1211,
        1348,
        1550
    ],
    "789": [
        1216,
        1712
    ],
    "790": [
        1218,
        1599,
        1647
    ],
    "791": [
        1223
    ],
    "792": [
        1229,
        1387
    ],
    "793": [
        1230
    ],
    "794": [
        1231,
        1454,
        1525
    ],
    "795": [
        1232,
        1244,
        1264
    ],
    "796": [
        1235,
        1799
    ],
    "797": [
        1237
    ],
    "798": [
        1239,
        1300,
        1543
    ],
    "799": [
        1240
    ],
    "800": [
        1245
    ],
    "801": [
        1246
    ],
    "802": [
        1247
    ],
    "803": [
        1249
    ],
    "804": [
        1250
    ],
    "805": [
        1252
    ],
    "806": [
        1254
    ],
    "807": [
        1255,
        1840
    ],
    "808": [
        1258
    ],
    "809": [
        1259,
        1295,
        1597
    ],
    "810": [
        1260
    ],
    "811": [
        1262
    ],
    "812": [
        1266
    ],
    "813": [
        1267
    ],
    "814": [
        1269,
        1330,
        1379
    ],
    "815": [
        1270
    ],
    "816": [
        1271,
        1593,
        1633
    ],
    "817": [
        1272
    ],
    "818": [
        1273,
        1314,
        1711
    ],
    "819": [
        1274
    ],
    "820": [
        1278,
        1618
    ],
    "821": [
        1282
    ],
    "822": [
        1283,
        1354,
        1683
    ],
    "823": [
        1284
    ],
    "824": [
        1288
    ],
    "825": [
        1289
    ],
    "826": [
        1290,
        1598,
        1620
    ],
    "827": [
        1291
    ],
    "828": [
        1292
    ],
    "829": [
        1294
    ],
    "830": [
        1296
    ],
    "831": [
        1298
    ],
    "832": [
        1301
    ],
    "833": [
        1303
    ],
    "834": [
        1304
    ],
    "835": [
        1305,
        1841
    ],
    "836": [
        1307
    ],
    "837": [
        1308
    ],
    "838": [
        1312
    ],
    "839": [
        1315
    ],
    "840": [
        1318
    ],
    "841": [
        1319
    ],
    "842": [
        1320,
        1322,
        1350
    ],
    "843": [
        1321
    ],
    "844": [
        1323,
        1440
    ],
    "845": [
        1324,
        1604
    ],
    "846": [
        1326
    ],
    "847": [
        1327
    ],
    "848": [
        1328
    ],
    "849": [
        1329
    ],
    "850": [
        1335
    ],
    "851": [
        1336
    ],
    "852": [
        1337
    ],
    "853": [
        1338,
        1663
    ],
    "854": [
        1339
    ],
    "855": [
        1340
    ],
    "856": [
        1341,
        1606,
        1787
    ],
    "857": [
        1342
    ],
    "858": [
        1343,
        1608
    ],
    "859": [
        1344
    ],
    "860": [
        1345
    ],
    "861": [
        1347
    ],
    "862": [
        1349
    ],
    "863": [
        1355
    ],
    "864": [
        1359
    ],
    "865": [
        1363
    ],
    "866": [
        1364
    ],
    "867": [
        1365,
        1600
    ],
    "868": [
        1368,
        1658
    ],
    "869": [
        1370,
        1709,
        1803
    ],
    "870": [
        1371
    ],
    "871": [
        1373
    ],
    "872": [
        1374
    ],
    "873": [
        1376
    ],
    "874": [
        1377
    ],
    "875": [
        1378
    ],
    "876": [
        1380,
        1425,
        1428
    ],
    "877": [
        1381
    ],
    "878": [
        1382
    ],
    "879": [
        1383
    ],
    "880": [
        1384,
        1493,
        1572
    ],
    "881": [
        1385,
        1823
    ],
    "882": [
        1389
    ],
    "883": [
        1390
    ],
    "884": [
        1391
    ],
    "885": [
        1392,
        1794
    ],
    "886": [
        1394
    ],
    "887": [
        1395,
        1581
    ],
    "888": [
        1397
    ],
    "889": [
        1398
    ],
    "890": [
        1399
    ],
    "891": [
        1400
    ],
    "892": [
        1401
    ],
    "893": [
        1402,
        1460,
        1485
    ],
    "894": [
        1403
    ],
    "895": [
        1405,
        1515,
        1568
    ],
    "896": [
        1408,
        1790
    ],
    "897": [
        1409,
        1516
    ],
    "898": [
        1410,
        1573
    ],
    "899": [
        1411
    ],
    "900": [
        1413
    ],
    "901": [
        1414,
        1546,
        1556
    ],
    "902": [
        1415
    ],
    "903": [
        1416
    ],
    "904": [
        1420,
        1569
    ],
    "905": [
        1421
    ],
    "906": [
        1422
    ],
    "907": [
        1426,
        1531,
        1890
    ],
    "908": [
        1427,
        1480,
        1748
    ],
    "909": [
        1429,
        1595
    ],
    "910": [
        1430
    ],
    "911": [
        1431
    ],
    "912": [
        1432,
        1594
    ],
    "913": [
        1438
    ],
    "914": [
        1439
    ],
    "915": [
        1443,
        1453
    ],
    "916": [
        1445
    ],
    "917": [
        1446,
        1796
    ],
    "918": [
        1448
    ],
    "919": [
        1450
    ],
    "920": [
        1451
    ],
    "921": [
        1452
    ],
    "922": [
        1455
    ],
    "923": [
        1456
    ],
    "924": [
        1458
    ],
    "925": [
        1459,
        1739
    ],
    "926": [
        1461,
        1708,
        1728
    ],
    "927": [
        1462
    ],
    "928": [
        1466,
        1576,
        1589
    ],
    "929": [
        1468
    ],
    "930": [
        1469,
        1571,
        1853
    ],
    "931": [
        1471
    ],
    "932": [
        1472,
        1917
    ],
    "933": [
        1473
    ],
    "934": [
        1474,
        1657
    ],
    "935": [
        1475
    ],
    "936": [
        1476,
        1496
    ],
    "937": [
        1477
    ],
    "938": [
        1478,
        1807
    ],
    "939": [
        1482
    ],
    "940": [
        1483
    ],
    "941": [
        1486
    ],
    "942": [
        1487
    ],
    "943": [
        1489
    ],
    "944": [
        1490,
        1757,
        1889
    ],
    "945": [
        1491
    ],
    "946": [
        1492
    ],
    "947": [
        1494
    ],
    "948": [
        1495
    ],
    "949": [
        1497
    ],
    "950": [
        1499
    ],
    "951": [
        1502,
        1899
    ],
    "952": [
        1503
    ],
    "953": [
        1504
    ],
    "954": [
        1506
    ],
    "955": [
        1508,
        1545,
        1563
    ],
    "956": [
        1514
    ],
    "957": [
        1517
    ],
    "958": [
        1524
    ],
    "959": [
        1526
    ],
    "960": [
        1527,
        1713
    ],
    "961": [
        1529
    ],
    "962": [
        1530
    ],
    "963": [
        1532,
        1927
    ],
    "964": [
        1533
    ],
    "965": [
        1534
    ],
    "966": [
        1536,
        1574,
        1700
    ],
    "967": [
        1537
    ],
    "968": [
        1539
    ],
    "969": [
        1541
    ],
    "970": [
        1542
    ],
    "971": [
        1548
    ],
    "972": [
        1549
    ],
    "973": [
        1552,
        1719
    ],
    "974": [
        1554
    ],
    "975": [
        1555
    ],
    "976": [
        1559,
        1607
    ],
    "977": [
        1562,
        1911
    ],
    "978": [
        1565
    ],
    "979": [
        1566
    ],
    "980": [
        1567
    ],
    "981": [
        1570,
        1806
    ],
    "982": [
        1577
    ],
    "983": [
        1578
    ],
    "984": [
        1579
    ],
    "985": [
        1580,
        1636,
        1753
    ],
    "986": [
        1586
    ],
    "987": [
        1588
    ],
    "988": [
        1590
    ],
    "989": [
        1591,
        1623,
        1702
    ],
    "990": [
        1592,
        1692,
        1887
    ],
    "991": [
        1596
    ],
    "992": [
        1601,
        1616,
        1659
    ],
    "993": [
        1602
    ],
    "994": [
        1609,
        1734,
        1831
    ],
    "995": [
        1610,
        1690,
        1691
    ],
    "996": [
        1612
    ],
    "997": [
        1615,
        1638,
        1643
    ],
    "998": [
        1617,
        1660,
        1786
    ],
    "999": [
        1619,
        1635,
        1726
    ],
    "1000": [
        1622
    ],
    "1001": [
        1625,
        1697
    ],
    "1002": [
        1626,
        1717
    ],
    "1003": [
        1627
    ],
    "1004": [
        1631
    ],
    "1005": [
        1632
    ],
    "1006": [
        1637
    ],
    "1007": [
        1639,
        1932
    ],
    "1008": [
        1641
    ],
    "1009": [
        1645,
        1769,
        1909
    ],
    "1010": [
        1646
    ],
    "1011": [
        1650
    ],
    "1012": [
        1651
    ],
    "1013": [
        1652
    ],
    "1014": [
        1654
    ],
    "1015": [
        1655
    ],
    "1016": [
        1656
    ],
    "1017": [
        1661
    ],
    "1018": [
        1662
    ],
    "1019": [
        1664,
        1744
    ],
    "1020": [
        1666
    ],
    "1021": [
        1667
    ],
    "1022": [
        1670,
        1733
    ],
    "1023": [
        1671
    ],
    "1024": [
        1673
    ],
    "1025": [
        1674
    ],
    "1026": [
        1675
    ],
    "1027": [
        1676
    ],
    "1028": [
        1677
    ],
    "1029": [
        1678
    ],
    "1030": [
        1679
    ],
    "1031": [
        1680
    ],
    "1032": [
        1682
    ],
    "1033": [
        1684
    ],
    "1034": [
        1686
    ],
    "1035": [
        1687
    ],
    "1036": [
        1688
    ],
    "1037": [
        1689,
        1704,
        1724
    ],
    "1038": [
        1693,
        1836
    ],
    "1039": [
        1694
    ],
    "1040": [
        1696
    ],
    "1041": [
        1698,
        1818
    ],
    "1042": [
        1701
    ],
    "1043": [
        1705
    ],
    "1044": [
        1706,
        1858,
        1902
    ],
    "1045": [
        1710
    ],
    "1046": [
        1714
    ],
    "1047": [
        1716
    ],
    "1048": [
        1718,
        1752,
        1934
    ],
    "1049": [
        1720,
        1837
    ],
    "1050": [
        1723
    ],
    "1051": [
        1725
    ],
    "1052": [
        1727
    ],
    "1053": [
        1730
    ],
    "1054": [
        1731
    ],
    "1055": [
        1732
    ],
    "1056": [
        1736,
        1845,
        1883
    ],
    "1057": [
        1737
    ],
    "1058": [
        1738
    ],
    "1059": [
        1741
    ],
    "1060": [
        1742
    ],
    "1061": [
        1746
    ],
    "1062": [
        1747
    ],
    "1063": [
        1749
    ],
    "1064": [
        1750,
        1800,
        1907
    ],
    "1065": [
        1758
    ],
    "1066": [
        1760
    ],
    "1067": [
        1761
    ],
    "1068": [
        1762
    ],
    "1069": [
        1763
    ],
    "1070": [
        1764
    ],
    "1071": [
        1765
    ],
    "1072": [
        1766,
        1804,
        1826
    ],
    "1073": [
        1767
    ],
    "1074": [
        1768
    ],
    "1075": [
        1770
    ],
    "1076": [
        1771
    ],
    "1077": [
        1772
    ],
    "1078": [
        1773
    ],
    "1079": [
        1774
    ],
    "1080": [
        1775
    ],
    "1081": [
        1776
    ],
    "1082": [
        1777
    ],
    "1083": [
        1778
    ],
    "1084": [
        1780
    ],
    "1085": [
        1781,
        1821
    ],
    "1086": [
        1783
    ],
    "1087": [
        1784
    ],
    "1088": [
        1785
    ],
    "1089": [
        1788,
        1838
    ],
    "1090": [
        1789
    ],
    "1091": [
        1791
    ],
    "1092": [
        1793
    ],
    "1093": [
        1801
    ],
    "1094": [
        1805
    ],
    "1095": [
        1808
    ],
    "1096": [
        1809
    ],
    "1097": [
        1810
    ],
    "1098": [
        1811
    ],
    "1099": [
        1815
    ],
    "1100": [
        1816
    ],
    "1101": [
        1819
    ],
    "1102": [
        1820
    ],
    "1103": [
        1822
    ],
    "1104": [
        1827
    ],
    "1105": [
        1830
    ],
    "1106": [
        1832
    ],
    "1107": [
        1833
    ],
    "1108": [
        1834
    ],
    "1109": [
        1835
    ],
    "1110": [
        1839,
        1912
    ],
    "1111": [
        1842
    ],
    "1112": [
        1843
    ],
    "1113": [
        1847
    ],
    "1114": [
        1848
    ],
    "1115": [
        1849
    ],
    "1116": [
        1850
    ],
    "1117": [
        1851
    ],
    "1118": [
        1852
    ],
    "1119": [
        1854
    ],
    "1120": [
        1855
    ],
    "1121": [
        1856
    ],
    "1122": [
        1859
    ],
    "1123": [
        1861
    ],
    "1124": [
        1863
    ],
    "1125": [
        1864
    ],
    "1126": [
        1865
    ],
    "1127": [
        1866
    ],
    "1128": [
        1868
    ],
    "1129": [
        1870
    ],
    "1130": [
        1871
    ],
    "1131": [
        1874
    ],
    "1132": [
        1876
    ],
    "1133": [
        1879
    ],
    "1134": [
        1880
    ],
    "1135": [
        1881
    ],
    "1136": [
        1882
    ],
    "1137": [
        1888
    ],
    "1138": [
        1891
    ],
    "1139": [
        1892
    ],
    "1140": [
        1893
    ],
    "1141": [
        1895
    ],
    "1142": [
        1896
    ],
    "1143": [
        1897
    ],
    "1144": [
        1900
    ],
    "1145": [
        1901
    ],
    "1146": [
        1905
    ],
    "1147": [
        1906
    ],
    "1148": [
        1915
    ],
    "1149": [
        1916
    ],
    "1150": [
        1918
    ],
    "1151": [
        1920
    ],
    "1152": [
        1921
    ],
    "1153": [
        1922
    ],
    "1154": [
        1923
    ],
    "1155": [
        1924
    ],
    "1156": [
        1926
    ],
    "1157": [
        1929
    ],
    "1158": [
        1930
    ],
    "1159": [
        1931
    ]
}